apitopy.py
apitopy-0.6.0.dist-info/METADATA
apitopy-0.6.0.dist-info/WHEEL
apitopy-0.6.0.dist-info/top_level.txt
apitopy-0.6.0.dist-info/RECORD
